maketool/__init__.py
maketool/build.py
maketool/clean.py
maketool/compile.py
maketool/refscan.py
maketool/run.py
maketool/sublime.py
maketool-0.8.24.dist-info/METADATA
maketool-0.8.24.dist-info/WHEEL
maketool-0.8.24.dist-info/entry_points.txt
maketool-0.8.24.dist-info/top_level.txt
maketool-0.8.24.dist-info/RECORD
