Metadata-Version: 2.4
Name: maketool
Version: 0.8.24
Summary: Python Automation tool for building PySide6 UI and PyInstaller EXE.
Author-email: Alan Lilly <panofish@gmail.com>
Requires-Python: >=3.7
